taurex_instrumentsystematics/__init__.py
taurex_instrumentsystematics/instr_binner.py
taurex_instrumentsystematics/instr_offset.py
taurex_instrumentsystematics/offset.py
taurex_instrumentsystematics-1.0.0.dist-info/licenses/LICENSE
taurex_instrumentsystematics-1.0.0.dist-info/METADATA
taurex_instrumentsystematics-1.0.0.dist-info/WHEEL
taurex_instrumentsystematics-1.0.0.dist-info/entry_points.txt
taurex_instrumentsystematics-1.0.0.dist-info/top_level.txt
taurex_instrumentsystematics-1.0.0.dist-info/RECORD
