Metadata-Version: 2.4
Name: taurex_instrumentsystematics
Version: 1.0.0
Summary: Add multiple spectra and Instrument Systematics fitting to TauREx 3.1
Home-page: https://github.com/groningen-exoatmospheres/taurex-instrumentsystematics
Author: Quentin Changeat
Author-email: q.changeat@rug.nl
License: BSD
Provides: taurex_instrumentsystematics
License-File: LICENSE
Requires-Dist: taurex
Dynamic: author
Dynamic: author-email
Dynamic: home-page
Dynamic: license
Dynamic: license-file
Dynamic: provides
Dynamic: requires-dist
Dynamic: summary
